gpu4u/__init__.py
gpu4u/__main__.py
gpu4u-0.2.0.dist-info/LICENSE
gpu4u-0.2.0.dist-info/METADATA
gpu4u-0.2.0.dist-info/WHEEL
gpu4u-0.2.0.dist-info/top_level.txt
gpu4u-0.2.0.dist-info/RECORD
