Metadata-Version: 2.1
Name: gpu4u
Version: 0.2.0
Summary: A Python Package for Automatically Monitoring & Occupying NVIDIA GPUs
Home-page: https://github.com/imrdong/gpu4u
Author: mrdong
Maintainer: mrdong
License: GPL-3.0
Platform: UNKNOWN
Classifier: License :: OSI Approved :: GNU General Public License v3 (GPLv3)
Classifier: Operating System :: OS Independent
Classifier: Programming Language :: Python :: 3
Requires-Dist: pynvml
Requires-Dist: requests
